AUTHORS.md
CHANGELOG.md
CONTRIBUTING.md
MANIFEST.in
README.md
setup.cfg
setup.py
headercop/__init__.py
headercop/cli.py
headercop/headercop.py
headercop.egg-info/PKG-INFO
headercop.egg-info/SOURCES.txt
headercop.egg-info/dependency_links.txt
headercop.egg-info/entry_points.txt
headercop.egg-info/not-zip-safe
headercop.egg-info/requires.txt
headercop.egg-info/top_level.txt
headercop/licenses/bsd3.txt
tests/__init__.py
tests/test_cli.py
tests/test_headercop.py