Metadata-Version: 1.1
Name: headercop
Version: 0.1.1
Summary: Enforce license headers in files
Home-page: https://gitlab.com/kaffi/headercop
Author: Kaffi LLC
Author-email: paul.collins@kaffi.io
License: BSD license
Keywords: headercop
Platform: UNKNOWN
Classifier: Development Status :: 2 - Pre-Alpha
Classifier: Intended Audience :: Developers
Classifier: License :: OSI Approved :: BSD License
Classifier: Natural Language :: English
Classifier: Programming Language :: Python :: 3
Classifier: Programming Language :: Python :: 3.5
